{"updated":"2026-07-08T18:42:10.722Z","sections":{"friday_goals":{"v":[{"t":"Vermessungskunde-Klausur bestehen","cat":"STUDIUM","pct":50},{"t":"Zimmerer-Praxis mit Studium verzahnen","cat":"KARRIERE","pct":40},{"t":"Regelmäßig trainieren","cat":"GESUNDHEIT","pct":30}],"ts":1783536128921},"friday_decisions":{"v":{"94d16c8cbec6":{"status":"rejected","title":"[ILIAS] PVL Prüfung 220063 - Feldübung VK","date":"2026-08-07","time":null,"decidedAt":"2026-07-06T08:33:48.326Z"}},"ts":1783326828326},"friday_body":{"v":{"state":"cut","weight":"110","height":"180","age":"24","sex":"m"},"ts":1783424800623}}}